pathier/__init__.py
pathier/pathier.py
pathier/py.typed
pathier-1.5.4.dist-info/METADATA
pathier-1.5.4.dist-info/WHEEL
pathier-1.5.4.dist-info/entry_points.txt
pathier-1.5.4.dist-info/licenses/LICENSE.txt
pathier-1.5.4.dist-info/RECORD
