Metadata-Version: 2.3
Name: pathier
Version: 1.5.4
Summary: Extends the standard library pathlib.Path class.
Project-URL: Homepage, https://github.com/matt-manes/pathier
Project-URL: Documentation, https://github.com/matt-manes/pathier/tree/main/docs
Project-URL: Source code, https://github.com/matt-manes/pathier/tree/main/src/pathier
Author-email: Matt Manes <mattmanes@pm.me>
License-File: LICENSE.txt
Keywords: extender,extension,json,path,pathlib,shutil,toml
Classifier: License :: OSI Approved :: MIT License
Classifier: Operating System :: OS Independent
Classifier: Programming Language :: Python :: 3
Requires-Python: <3.12,>=3.10
Requires-Dist: griddle
Requires-Dist: noiftimer
Requires-Dist: printbuddies
Requires-Dist: tomlkit>=0.11.8
Requires-Dist: typing-extensions
Requires-Dist: younotyou
